LRGpy.py
__init__.py
helper.py
registration.py
segmentation.py
src/__init__.py
src/helper.py
src/registration.py
src/segmentation.py
LRGpy-0.1.0.dist-info/LICENSE.txt
LRGpy-0.1.0.dist-info/METADATA
LRGpy-0.1.0.dist-info/WHEEL
LRGpy-0.1.0.dist-info/top_level.txt
LRGpy-0.1.0.dist-info/RECORD
