Metadata-Version: 2.1
Name: LRGpy
Version: 0.1.0
Summary: LRG Python code repsository.
Home-page: https://github.com/GMU-LRG/LRGpy
Author: Lattanzi Research Group
Author-email: dlattanz@gmu.edu
License: UNKNOWN
Platform: UNKNOWN
Classifier: Programming Language :: Python :: 3
Classifier: Programming Language :: Python :: 3.6
Classifier: Programming Language :: Python :: 3.7
Classifier: License :: OSI Approved :: MIT License
Classifier: Operating System :: OS Independent
Classifier: Natural Language :: English
Classifier: Topic :: Scientific/Engineering
Requires-Dist: scikit-learn
Requires-Dist: matplotlib
